teleserver/__init__.py
teleserver/keyboard_cli.py
teleserver/login_cli.py
teleserver/requests_handler.py
teleserver/system_cli.py
teleserver/teleserver.py
teleserver/webbrowser_cli.py
teleserver/tests/__init__.py
teleserver/tests/test_requests_handler.py
teleserver/utils/__init__.py
teleserver/utils/lookup_utils.py
teleserver/utils/tests/__init__.py
teleserver/utils/tests/test_lookup_utils.py
teleserver-1.0.1.dist-info/LICENSE
teleserver-1.0.1.dist-info/METADATA
teleserver-1.0.1.dist-info/WHEEL
teleserver-1.0.1.dist-info/entry_points.txt
teleserver-1.0.1.dist-info/top_level.txt
teleserver-1.0.1.dist-info/RECORD
