Metadata-Version: 2.1
Name: teleserver
Version: 1.0.1
Summary: CLI tool to teleserver project.
Home-page: https://github.com/Dysproz/teleserver
Author: Szymon Piotr Krasuski
License: UNKNOWN
Platform: UNKNOWN
Classifier: Programming Language :: Python :: 3
Classifier: License :: OSI Approved :: MIT License
Classifier: Operating System :: OS Independent
Requires-Python: >=3.6
Requires-Dist: click
Requires-Dist: eventlet (==0.25.1)
Requires-Dist: ipaddress (==1.0.23)
Requires-Dist: netifaces (==0.10.9)
Requires-Dist: requests
